loop_rate_limiters/__init__.py
loop_rate_limiters/async_rate_limiter.py
loop_rate_limiters/rate_limiter.py
loop_rate_limiters-1.1.2.dist-info/LICENSE
loop_rate_limiters-1.1.2.dist-info/WHEEL
loop_rate_limiters-1.1.2.dist-info/METADATA
loop_rate_limiters-1.1.2.dist-info/RECORD
