Metadata-Version: 2.1
Name: loop-rate-limiters
Version: 1.1.2
Summary: Loop rate limiters.
Keywords: rate,loop,frequency,regulator,limiter
Author-email: Stéphane Caron <stephane.caron@normalesup.org>
Maintainer-email: Stéphane Caron <stephane.caron@normalesup.org>
Requires-Python: >=3.8
Classifier: Development Status :: 5 - Production/Stable
Classifier: Intended Audience :: Developers
Classifier: Intended Audience :: Science/Research
Classifier: License :: OSI Approved :: Apache Software License
Classifier: Operating System :: OS Independent
Classifier: Programming Language :: Python :: 3.9
Classifier: Programming Language :: Python :: 3.10
Classifier: Programming Language :: Python :: 3.11
Classifier: Programming Language :: Python :: 3.12
Classifier: Topic :: Scientific/Engineering :: Mathematics
Project-URL: Changelog, https://github.com/stephane-caron/loop-rate-limiters/blob/master/CHANGELOG.md
Project-URL: Homepage, https://github.com/stephane-caron/loop-rate-limiters
Project-URL: Source, https://github.com/stephane-caron/loop-rate-limiters
Project-URL: Tracker, https://github.com/stephane-caron/loop-rate-limiters/issues
